gguf2gui-0.1.3.dist-info/licenses/LICENSE
gguf_converter/__init__.py
gguf_converter/__main__.py
gguf_converter/convert-legacy-llama.py
gguf_converter/gui.py
gguf2gui-0.1.3.dist-info/METADATA
gguf2gui-0.1.3.dist-info/WHEEL
gguf2gui-0.1.3.dist-info/entry_points.txt
gguf2gui-0.1.3.dist-info/top_level.txt
gguf2gui-0.1.3.dist-info/RECORD
