Metadata-Version: 2.4
Name: gguf2gui
Version: 0.1.3
Summary: A modern GUI tool to convert HuggingFace safetensors to GGUF
Author: Your Name
License: MIT
License-File: LICENSE
Requires-Dist: customtkinter
Requires-Dist: gguf
Requires-Dist: numpy>=1.20
Requires-Dist: tqdm>=4.27
Requires-Dist: sentencepiece<=0.2.0,>=0.1.98
Requires-Dist: pyyaml>=5.1
Dynamic: license-file
